{
 "id": "a3f9c2b7e1",
 "shelf_tag": "Hybrid",
 "confidence": "strong",
 "dominant": [
  "Linalool",
  "Limonene",
  "beta-Caryophyllene"
 ],
 "terpenes": {
  "beta-Caryophyllene": 0.31,
  "beta-Myrcene": 0.23,
  "Farnesene": 0.11,
  "Linalool": 0.58,
  "Alpha-cedrene": 0.06,
  "beta-Pinene": 0.09,
  "alpha-Humulene": 0.09,
  "Terpineol": 0.09,
  "trans-Nerolidol": 0.06,
  "Fenchol": 0.1,
  "Limonene": 0.47
 },
 "brand": "Smartbud",
 "total_terpenes": 2.19,
 "metrc_tag": "1A41203000003F6000000859",
 "reported": [
  "28.6% Total THC",
  "2.19% Total Terpenes"
 ],
 "aroma": [
  "floral",
  "citrus",
  "spicy",
  "herbal",
  "piney"
 ],
 "form": "Flower 3.5g",
 "strain": "Georgia Z",
 "lean": "mixed",
 "in_stock": true,
 "thc": 28.638
}